ipcx_typed/__init__.py
ipcx_typed/_types.py
ipcx_typed/client.py
ipcx_typed/errors.py
ipcx_typed/models.py
ipcx_typed/server.py
ipcx_typed-0.1.5.dist-info/LICENSE
ipcx_typed-0.1.5.dist-info/METADATA
ipcx_typed-0.1.5.dist-info/WHEEL
ipcx_typed-0.1.5.dist-info/RECORD
