Metadata-Version: 2.3
Name: ipcx-typed
Version: 0.1.5
Summary: Inter-Process Communication (IPC) library for Python with type safety
License: MIT
Keywords: ipc,ipcx,ipcx-typed,ipcx-typed-python,discord.py,fastapi,python,asyncio,networking
Author: zakharfsk
Author-email: 68950796+zakharfsk@users.noreply.github.com
Requires-Python: >=3.12
Classifier: Development Status :: 4 - Beta
Classifier: Framework :: AsyncIO
Classifier: Framework :: Pydantic
Classifier: Framework :: Pydantic :: 2
Classifier: Intended Audience :: Developers
Classifier: License :: OSI Approved :: MIT License
Classifier: Natural Language :: English
Classifier: Operating System :: OS Independent
Classifier: Programming Language :: Python :: 3.9
Classifier: Programming Language :: Python :: 3.10
Classifier: Programming Language :: Python :: 3.11
Classifier: Programming Language :: Python :: 3.12
Classifier: Programming Language :: Python :: 3.13
Classifier: Programming Language :: Python :: Implementation :: CPython
Classifier: Topic :: Internet
Classifier: Topic :: Software Development :: Libraries
Classifier: Topic :: Software Development :: Libraries :: Python Modules
Classifier: Topic :: Utilities
Classifier: Typing :: Typed
Requires-Dist: aiohttp (>=3.11.18,<4.0.0)
Requires-Dist: pydantic (>=2.11.4,<3.0.0)
Project-URL: Documentation, https://github.com/zakharfsk/ipcx-typed/blob/main/README.md
Project-URL: Homepage, https://github.com/zakharfsk/ipcx-typed
Project-URL: Issue, https://github.com/zakharfsk/ipcx-typed/issues
Project-URL: Repository, https://github.com/zakharfsk/ipcx-typed
